README.txt
setup.cfg
setup.py
Products/__init__.py
Products.PloneStatCounter.egg-info/PKG-INFO
Products.PloneStatCounter.egg-info/SOURCES.txt
Products.PloneStatCounter.egg-info/dependency_links.txt
Products.PloneStatCounter.egg-info/entry_points.txt
Products.PloneStatCounter.egg-info/namespace_packages.txt
Products.PloneStatCounter.egg-info/not-zip-safe
Products.PloneStatCounter.egg-info/requires.txt
Products.PloneStatCounter.egg-info/top_level.txt
Products/PloneStatCounter/__init__.py
Products/PloneStatCounter/browser.py
Products/PloneStatCounter/configure.zcml
Products/PloneStatCounter/interfaces.py
Products/PloneStatCounter/setuphandlers.py
Products/PloneStatCounter/statcounter.pt
Products/PloneStatCounter/tests.py
Products/PloneStatCounter/utility.py
Products/PloneStatCounter/viewlets.py
Products/PloneStatCounter/profiles/default/controlpanel.xml
Products/PloneStatCounter/profiles/default/import_steps.xml
Products/PloneStatCounter/profiles/default/viewlets.xml
docs/HISTORY.txt
docs/INSTALL.txt
docs/LICENSE.GPL
docs/LICENSE.txt
