Metadata-Version: 1.0
Name: Products.PloneStatCounter
Version: 0.1
Summary: A package to ease use of StatCounter in Plone.
Home-page: http://svn.plone.org/svn/collective/Products.PloneStatCounter
Author: Tim Hicks
Author-email: tim@sitefusion.co.uk
License: GPL
Platform: UNKNOWN
Classifier: Framework :: Plone
Classifier: Framework :: Zope2
Classifier: Framework :: Zope3
Classifier: Programming Language :: Python
Classifier: Topic :: Software Development :: Libraries :: Python Modules
